{
  "id": "capacity_utilization",
  "name": "Capacity Utilization",
  "fred_ticker": "TCU",
  "category": "activity",
  "page": "cycle",
  "tier": 3,
  "weight": 1,
  "frequency": "monthly",
  "unit": "percent",
  "source_type": "fred",
  "last_updated": "2026-06-16T17:52:41.085193+00:00",
  "current_value": 76.1663,
  "previous_value": 76.1289,
  "data": [
    {
      "date": "2026-05-01",
      "value": 76.1663
    },
    {
      "date": "2026-04-01",
      "value": 76.1289
    },
    {
      "date": "2026-03-01",
      "value": 75.5388
    },
    {
      "date": "2026-02-01",
      "value": 75.847
    },
    {
      "date": "2026-01-01",
      "value": 75.305
    },
    {
      "date": "2025-12-01",
      "value": 75.6422
    },
    {
      "date": "2025-11-01",
      "value": 75.3901
    },
    {
      "date": "2025-10-01",
      "value": 75.6194
    },
    {
      "date": "2025-09-01",
      "value": 76.0461
    },
    {
      "date": "2025-08-01",
      "value": 76.1055
    },
    {
      "date": "2025-07-01",
      "value": 76.3997
    },
    {
      "date": "2025-06-01",
      "value": 76.181
    },
    {
      "date": "2025-05-01",
      "value": 75.8894
    },
    {
      "date": "2025-04-01",
      "value": 76.1048
    },
    {
      "date": "2025-03-01",
      "value": 76.1318
    },
    {
      "date": "2025-02-01",
      "value": 76.2685
    },
    {
      "date": "2025-01-01",
      "value": 75.5781
    },
    {
      "date": "2024-12-01",
      "value": 75.8651
    },
    {
      "date": "2024-11-01",
      "value": 75.1681
    },
    {
      "date": "2024-10-01",
      "value": 75.3852
    },
    {
      "date": "2024-09-01",
      "value": 75.7216
    },
    {
      "date": "2024-08-01",
      "value": 76.2697
    },
    {
      "date": "2024-07-01",
      "value": 75.9946
    },
    {
      "date": "2024-06-01",
      "value": 76.7586
    },
    {
      "date": "2024-05-01",
      "value": 76.7961
    },
    {
      "date": "2024-04-01",
      "value": 76.3803
    },
    {
      "date": "2024-03-01",
      "value": 76.5964
    },
    {
      "date": "2024-02-01",
      "value": 76.5157
    },
    {
      "date": "2024-01-01",
      "value": 75.7542
    },
    {
      "date": "2023-12-01",
      "value": 76.858
    },
    {
      "date": "2023-11-01",
      "value": 77.1081
    },
    {
      "date": "2023-10-01",
      "value": 76.859
    },
    {
      "date": "2023-09-01",
      "value": 77.3375
    },
    {
      "date": "2023-08-01",
      "value": 77.2588
    },
    {
      "date": "2023-07-01",
      "value": 77.3773
    },
    {
      "date": "2023-06-01",
      "value": 76.8467
    },
    {
      "date": "2023-05-01",
      "value": 77.5496
    },
    {
      "date": "2023-04-01",
      "value": 77.888
    },
    {
      "date": "2023-03-01",
      "value": 77.8036
    },
    {
      "date": "2023-02-01",
      "value": 77.6078
    },
    {
      "date": "2023-01-01",
      "value": 77.601
    },
    {
      "date": "2022-12-01",
      "value": 77.1334
    },
    {
      "date": "2022-11-01",
      "value": 78.1544
    },
    {
      "date": "2022-10-01",
      "value": 78.4843
    },
    {
      "date": "2022-09-01",
      "value": 78.6087
    },
    {
      "date": "2022-08-01",
      "value": 78.5438
    },
    {
      "date": "2022-07-01",
      "value": 78.7204
    },
    {
      "date": "2022-06-01",
      "value": 78.6259
    },
    {
      "date": "2022-05-01",
      "value": 78.9224
    },
    {
      "date": "2022-04-01",
      "value": 79.0418
    },
    {
      "date": "2022-03-01",
      "value": 79.0253
    },
    {
      "date": "2022-02-01",
      "value": 78.5777
    },
    {
      "date": "2022-01-01",
      "value": 78.088
    },
    {
      "date": "2021-12-01",
      "value": 78.3687
    },
    {
      "date": "2021-11-01",
      "value": 78.562
    },
    {
      "date": "2021-10-01",
      "value": 77.9838
    },
    {
      "date": "2021-09-01",
      "value": 76.8871
    },
    {
      "date": "2021-08-01",
      "value": 77.7308
    },
    {
      "date": "2021-07-01",
      "value": 77.7972
    },
    {
      "date": "2021-06-01",
      "value": 77.3367
    },
    {
      "date": "2021-05-01",
      "value": 76.931
    },
    {
      "date": "2021-04-01",
      "value": 76.1216
    },
    {
      "date": "2021-03-01",
      "value": 75.8472
    },
    {
      "date": "2021-02-01",
      "value": 73.5725
    },
    {
      "date": "2021-01-01",
      "value": 75.9401
    },
    {
      "date": "2020-12-01",
      "value": 75.3903
    },
    {
      "date": "2020-11-01",
      "value": 74.2637
    },
    {
      "date": "2020-10-01",
      "value": 73.8636
    },
    {
      "date": "2020-09-01",
      "value": 73.1451
    },
    {
      "date": "2020-08-01",
      "value": 73.0192
    },
    {
      "date": "2020-07-01",
      "value": 72.2103
    },
    {
      "date": "2020-06-01",
      "value": 69.5218
    },
    {
      "date": "2020-05-01",
      "value": 65.1874
    },
    {
      "date": "2020-04-01",
      "value": 64.0847
    },
    {
      "date": "2020-03-01",
      "value": 73.7887
    },
    {
      "date": "2020-02-01",
      "value": 76.7764
    },
    {
      "date": "2020-01-01",
      "value": 76.519
    },
    {
      "date": "2019-12-01",
      "value": 77.0416
    },
    {
      "date": "2019-11-01",
      "value": 77.252
    },
    {
      "date": "2019-10-01",
      "value": 76.9099
    },
    {
      "date": "2019-09-01",
      "value": 77.6205
    },
    {
      "date": "2019-08-01",
      "value": 77.9497
    },
    {
      "date": "2019-07-01",
      "value": 77.4935
    },
    {
      "date": "2019-06-01",
      "value": 77.9493
    },
    {
      "date": "2019-05-01",
      "value": 77.9962
    },
    {
      "date": "2019-04-01",
      "value": 77.9898
    },
    {
      "date": "2019-03-01",
      "value": 78.5337
    },
    {
      "date": "2019-02-01",
      "value": 78.5877
    },
    {
      "date": "2019-01-01",
      "value": 79.1024
    },
    {
      "date": "2018-12-01",
      "value": 79.7142
    },
    {
      "date": "2018-11-01",
      "value": 79.7722
    },
    {
      "date": "2018-10-01",
      "value": 79.7802
    },
    {
      "date": "2018-09-01",
      "value": 79.9314
    },
    {
      "date": "2018-08-01",
      "value": 79.9322
    },
    {
      "date": "2018-07-01",
      "value": 79.4588
    },
    {
      "date": "2018-06-01",
      "value": 79.356
    },
    {
      "date": "2018-05-01",
      "value": 78.7526
    },
    {
      "date": "2018-04-01",
      "value": 79.4597
    },
    {
      "date": "2018-03-01",
      "value": 78.5697
    },
    {
      "date": "2018-02-01",
      "value": 78.1508
    },
    {
      "date": "2018-01-01",
      "value": 77.9138
    },
    {
      "date": "2017-12-01",
      "value": 77.8538
    },
    {
      "date": "2017-11-01",
      "value": 77.6337
    },
    {
      "date": "2017-10-01",
      "value": 77.3753
    },
    {
      "date": "2017-09-01",
      "value": 76.3591
    },
    {
      "date": "2017-08-01",
      "value": 76.2067
    },
    {
      "date": "2017-07-01",
      "value": 76.4534
    },
    {
      "date": "2017-06-01",
      "value": 76.5758
    },
    {
      "date": "2017-05-01",
      "value": 76.368
    },
    {
      "date": "2017-04-01",
      "value": 76.2392
    },
    {
      "date": "2017-03-01",
      "value": 75.4439
    },
    {
      "date": "2017-02-01",
      "value": 74.9346
    },
    {
      "date": "2017-01-01",
      "value": 75.2339
    },
    {
      "date": "2016-12-01",
      "value": 75.4424
    },
    {
      "date": "2016-11-01",
      "value": 74.9498
    },
    {
      "date": "2016-10-01",
      "value": 75.2918
    },
    {
      "date": "2016-09-01",
      "value": 75.3145
    },
    {
      "date": "2016-08-01",
      "value": 75.432
    },
    {
      "date": "2016-07-01",
      "value": 75.5839
    },
    {
      "date": "2016-06-01",
      "value": 75.5298
    },
    {
      "date": "2016-05-01",
      "value": 75.2034
    },
    {
      "date": "2016-04-01",
      "value": 75.3969
    },
    {
      "date": "2016-03-01",
      "value": 75.1587
    },
    {
      "date": "2016-02-01",
      "value": 75.7291
    },
    {
      "date": "2016-01-01",
      "value": 76.1248
    }
  ],
  "metadata": {
    "what_it_measures": "Total capacity utilization for all industries (Fed G.17).",
    "why_it_matters": "Above 80% = capacity constraints \u2192 margin compression risk. Below 78% (long-run average) = slack in the system, less inflation pressure.\n",
    "scoring_rule": "70-78% \u2192 neutral | >82% \u2192 -30 (overheating) | <70% \u2192 -50 (deep contraction). Phase 3."
  },
  "score": null,
  "next_expected_release": "2026-07-12T00:00:00+00:00",
  "zscore": {
    "level_z": -0.195,
    "level_mean": 76.615484,
    "level_std": 2.300206,
    "level_value_used": 76.1663,
    "trend_z": 0.143,
    "trend_value_used": 0.3193,
    "window": "10y",
    "transform": "level",
    "computed_at": "2026-06-16T20:34:03.141669+00:00"
  },
  "level_trend_state": "Neutral",
  "forecast": {
    "model": "SeasonalNaive",
    "horizon": 3,
    "values": [
      {
        "date": "2026-06-01",
        "mean": 76.181,
        "lo80": 71.8458,
        "hi80": 80.5162,
        "lo95": 69.5509,
        "hi95": 82.8111
      },
      {
        "date": "2026-07-01",
        "mean": 76.3997,
        "lo80": 72.0645,
        "hi80": 80.7349,
        "lo95": 69.7696,
        "hi95": 83.0298
      },
      {
        "date": "2026-08-01",
        "mean": 76.1055,
        "lo80": 71.7703,
        "hi80": 80.4407,
        "lo95": 69.4754,
        "hi95": 82.7356
      }
    ],
    "computed_at": "2026-06-16T17:53:53.586531+00:00"
  }
}